fi_instrumentation/README.md
fi_instrumentation/__init__.py
fi_instrumentation/fi_types.py
fi_instrumentation/instrumentation/__init__.py
fi_instrumentation/instrumentation/_attributes.py
fi_instrumentation/instrumentation/_protect_wrapper.py
fi_instrumentation/instrumentation/_spans.py
fi_instrumentation/instrumentation/_tracers.py
fi_instrumentation/instrumentation/_types.py
fi_instrumentation/instrumentation/config.py
fi_instrumentation/instrumentation/constants.py
fi_instrumentation/instrumentation/context_attributes.py
fi_instrumentation/instrumentation/helpers.py
fi_instrumentation/instrumentation/logging.py
fi_instrumentation/instrumentation/version.py
fi_instrumentation/otel.py
fi_instrumentation/settings.py
fi_instrumentation_otel-0.1.16.dist-info/METADATA
fi_instrumentation_otel-0.1.16.dist-info/WHEEL
fi_instrumentation_otel-0.1.16.dist-info/RECORD
