Metadata-Version: 2.3
Name: fi-instrumentation-otel
Version: 0.1.16
Summary: OpenTelemetry instrumentation
Author: Future AGI
Author-email: no-reply@futureagi.com
Requires-Python: >3.9,<3.14
Classifier: Programming Language :: Python :: 3
Classifier: Programming Language :: Python :: 3.10
Classifier: Programming Language :: Python :: 3.11
Classifier: Programming Language :: Python :: 3.12
Classifier: Programming Language :: Python :: 3.13
Provides-Extra: evaluation
Provides-Extra: grpc
Requires-Dist: ai-evaluation (>=0.1.0) ; extra == "evaluation"
Requires-Dist: futureagi (>=0.6.0) ; extra == "evaluation"
Requires-Dist: jsonschema (>=4.21.1,<5.0.0)
Requires-Dist: opentelemetry-api (>=1.29.0,<2.0.0)
Requires-Dist: opentelemetry-exporter-otlp-proto-grpc (>=1.29.0,<2.0.0) ; extra == "grpc"
Requires-Dist: opentelemetry-exporter-otlp-proto-http (>=1.29.0,<2.0.0)
Requires-Dist: opentelemetry-instrumentation
Requires-Dist: opentelemetry-sdk (>=1.29.0,<2.0.0)
Requires-Dist: pydantic (>=2.9.2,<3.0.0)
Requires-Dist: requests (>=2.32.3,<3.0.0)
Requires-Dist: typing-extensions (>=4.9.0,<5.0.0)
Requires-Dist: wrapt (>=1.15.0,<2.0.0)
